dgraphpandas/__init__.py
dgraphpandas/__main__.py
dgraphpandas/config.py
dgraphpandas/rdf.py
dgraphpandas/types.py
dgraphpandas/strategies/__init__.py
dgraphpandas/strategies/horizontal.py
dgraphpandas/strategies/schema.py
dgraphpandas/strategies/vertical.py
dgraphpandas/strategies/vertical_helpers.py
dgraphpandas/writers/__init__.py
dgraphpandas/writers/schema.py
dgraphpandas/writers/types.py
dgraphpandas/writers/upserts.py
tests/__init__.py
tests/test_config.py
tests/test_main.py
tests/test_rdf.py
tests/test_types.py
tests/strategies/__init__.py
tests/strategies/test_horizontal.py
tests/strategies/test_schema.py
tests/strategies/test_vertical.py
tests/strategies/test_vertical_helpers.py
tests/writers/__init__.py
tests/writers/test_schema.py
tests/writers/test_types.py
tests/writers/test_upserts.py
dgraphpandas-0.1.5.dist-info/LICENSE
dgraphpandas-0.1.5.dist-info/METADATA
dgraphpandas-0.1.5.dist-info/WHEEL
dgraphpandas-0.1.5.dist-info/entry_points.txt
dgraphpandas-0.1.5.dist-info/top_level.txt
dgraphpandas-0.1.5.dist-info/RECORD
