Metadata-Version: 2.1
Name: dgraphpandas
Version: 0.1.5
Summary: Transform Pandas DataFrames into Exports to be sent to DGraph
Home-page: https://github.com/kiran94/dgraphpandas
License: MIT
Keywords: dgraph,pandas,rdf,graph,database
Requires-Python: >=3.6
License-File: LICENSE
Requires-Dist: pandas<2
Requires-Dist: numpy<2
